pytest_aioworkers/__init__.py
pytest_aioworkers/plugin.py
pytest_aioworkers/py.typed
pytest_aioworkers/utils.py
pytest_aioworkers-0.5.0.dist-info/METADATA
pytest_aioworkers-0.5.0.dist-info/WHEEL
pytest_aioworkers-0.5.0.dist-info/entry_points.txt
pytest_aioworkers-0.5.0.dist-info/licenses/LICENSE
pytest_aioworkers-0.5.0.dist-info/RECORD
