Metadata-Version: 2.4
Name: pytest-aioworkers
Version: 0.5.0
Summary: A plugin to test aioworkers project with pytest
Project-URL: GitHub, https://github.com/aioworkers/pytest-aioworkers
Project-URL: Homepage, https://github.com/aioworkers/pytest-aioworkers
Project-URL: Documentation, https://github.com/aioworkers/pytest-aioworkers#readme
Project-URL: Issues, https://github.com/aioworkers/pytest-aioworkers/issues
Project-URL: Source, https://github.com/aioworkers/pytest-aioworkers
Author-email: Alexander Malev <malev@somedev.ru>
License-Expression: Apache-2.0
License-File: LICENSE
Keywords: aioworkers,pytest
Classifier: Development Status :: 5 - Production/Stable
Classifier: Framework :: AsyncIO
Classifier: Framework :: Pytest
Classifier: Intended Audience :: Developers
Classifier: License :: OSI Approved :: Apache Software License
Classifier: Programming Language :: Python :: 3
Classifier: Programming Language :: Python :: 3 :: Only
Classifier: Programming Language :: Python :: 3.9
Classifier: Programming Language :: Python :: 3.10
Classifier: Programming Language :: Python :: 3.11
Classifier: Programming Language :: Python :: 3.12
Classifier: Programming Language :: Python :: 3.13
Classifier: Programming Language :: Python :: Implementation :: CPython
Classifier: Programming Language :: Python :: Implementation :: PyPy
Classifier: Topic :: Software Development :: Testing
Classifier: Typing :: Typed
Requires-Python: >=3.9
Requires-Dist: aioworkers>=0.22
Requires-Dist: pytest>=8.3.4
Provides-Extra: aiohttp
Requires-Dist: pytest-aiohttp; extra == 'aiohttp'
Provides-Extra: asyncio
Requires-Dist: pytest-asyncio; extra == 'asyncio'
Provides-Extra: dev-lint
Requires-Dist: mypy==1.14.0; extra == 'dev-lint'
Requires-Dist: ruff==0.8.4; extra == 'dev-lint'
Provides-Extra: dev-test
Requires-Dist: aioworkers==0.28.0; extra == 'dev-test'
Requires-Dist: coverage[toml]==7.6.10; extra == 'dev-test'
Requires-Dist: pytest-asyncio==0.25.0; extra == 'dev-test'
Requires-Dist: pytest-mock==3.14.0; extra == 'dev-test'
Requires-Dist: pytest-timeout==2.3.1; extra == 'dev-test'
Requires-Dist: pytest==8.3.4; extra == 'dev-test'
Requires-Dist: pyyaml==6.0.2; extra == 'dev-test'
